py_landlock/__init__.py
py_landlock/abi.py
py_landlock/errors.py
py_landlock/flags.py
py_landlock/landlock.py
py_landlock/landlock_sys.py
py_landlock/libc.py
py_landlock/prctl.py
py_landlock/py.typed
py_landlock-0.1.1.dist-info/licenses/LICENSE
py_landlock-0.1.1.dist-info/METADATA
py_landlock-0.1.1.dist-info/WHEEL
py_landlock-0.1.1.dist-info/top_level.txt
py_landlock-0.1.1.dist-info/RECORD
