Metadata-Version: 2.4
Name: py-landlock
Version: 0.1.1
Summary: Python bindings for the Linux Landlock security module
Author-email: Sebastien Waegeneire <sebastien@Waegeneire.com>
License-Expression: MIT
Project-URL: repository, https://github.com/SebastienWae/py-landlock
Project-URL: issues, https://github.com/SebastienWae/py-landlock/issues
Keywords: landlock,linux,security,sandbox,seccomp
Classifier: Development Status :: 3 - Alpha
Classifier: Operating System :: POSIX :: Linux
Classifier: Programming Language :: Python :: 3.10
Classifier: Programming Language :: Python :: 3.11
Classifier: Programming Language :: Python :: 3.12
Classifier: Programming Language :: Python :: 3.13
Classifier: Topic :: Security
Classifier: Typing :: Typed
Requires-Python: >=3.10
License-File: LICENSE
Dynamic: license-file
